wemp/__init__.py
wemp/__main__.py
wemp/http.py
wemp-1.0.9.dist-info/METADATA
wemp-1.0.9.dist-info/WHEEL
wemp-1.0.9.dist-info/entry_points.txt
wemp-1.0.9.dist-info/top_level.txt
wemp-1.0.9.dist-info/RECORD
